nlm/__init__.py
nlm/__main__.py
nlm/ai_docs.py
nlm/cli/__init__.py
nlm/cli/alias.py
nlm/cli/auth.py
nlm/cli/chat.py
nlm/cli/config.py
nlm/cli/main.py
nlm/cli/notebook.py
nlm/cli/repl.py
nlm/cli/research.py
nlm/cli/source.py
nlm/cli/studio.py
nlm/core/__init__.py
nlm/core/alias.py
nlm/core/auth.py
nlm/core/auth_refresh.py
nlm/core/client.py
nlm/core/constants.py
nlm/core/exceptions.py
nlm/core/models.py
nlm/output/__init__.py
nlm/output/formatters.py
nlm/utils/__init__.py
nlm/utils/browser.py
nlm/utils/cdp.py
nlm/utils/config.py
notebooklm_cli-0.1.12.dist-info/METADATA
notebooklm_cli-0.1.12.dist-info/WHEEL
notebooklm_cli-0.1.12.dist-info/entry_points.txt
notebooklm_cli-0.1.12.dist-info/licenses/LICENSE
notebooklm_cli-0.1.12.dist-info/RECORD
